muon/__init__.py
muon/atac.py
muon/prot.py
muon/rna.py
muon/_atac/__init__.py
muon/_atac/io.py
muon/_atac/plot.py
muon/_atac/preproc.py
muon/_atac/tools.py
muon/_atac/utils.py
muon/_atac/_ref/jaspar/MA0002.2.pfm
muon/_atac/_ref/jaspar/MA0003.4.pfm
muon/_atac/_ref/jaspar/MA0004.1.pfm
muon/_atac/_ref/jaspar/MA0006.1.pfm
muon/_atac/_ref/jaspar/MA0007.3.pfm
muon/_atac/_ref/jaspar/MA0009.2.pfm
muon/_atac/_ref/jaspar/MA0014.3.pfm
muon/_atac/_ref/jaspar/MA0017.2.pfm
muon/_atac/_ref/jaspar/MA0018.4.pfm
muon/_atac/_ref/jaspar/MA0019.1.pfm
muon/_atac/_ref/jaspar/MA0024.3.pfm
muon/_atac/_ref/jaspar/MA0025.2.pfm
muon/_atac/_ref/jaspar/MA0027.2.pfm
muon/_atac/_ref/jaspar/MA0028.2.pfm
muon/_atac/_ref/jaspar/MA0029.1.pfm
muon/_atac/_ref/jaspar/MA0030.1.pfm
muon/_atac/_ref/jaspar/MA0031.1.pfm
muon/_atac/_ref/jaspar/MA0032.2.pfm
muon/_atac/_ref/jaspar/MA0033.2.pfm
muon/_atac/_ref/jaspar/MA0035.4.pfm
muon/_atac/_ref/jaspar/MA0036.3.pfm
muon/_atac/_ref/jaspar/MA0037.3.pfm
muon/_atac/_ref/jaspar/MA0038.2.pfm
muon/_atac/_ref/jaspar/MA0039.4.pfm
muon/_atac/_ref/jaspar/MA0040.1.pfm
muon/_atac/_ref/jaspar/MA0041.1.pfm
muon/_atac/_ref/jaspar/MA0042.2.pfm
muon/_atac/_ref/jaspar/MA0043.3.pfm
muon/_atac/_ref/jaspar/MA0046.2.pfm
muon/_atac/_ref/jaspar/MA0047.3.pfm
muon/_atac/_ref/jaspar/MA0048.2.pfm
muon/_atac/_ref/jaspar/MA0050.2.pfm
muon/_atac/_ref/jaspar/MA0051.1.pfm
muon/_atac/_ref/jaspar/MA0052.4.pfm
muon/_atac/_ref/jaspar/MA0056.2.pfm
muon/_atac/_ref/jaspar/MA0057.1.pfm
muon/_atac/_ref/jaspar/MA0058.3.pfm
muon/_atac/_ref/jaspar/MA0059.1.pfm
muon/_atac/_ref/jaspar/MA0060.3.pfm
muon/_atac/_ref/jaspar/MA0062.3.pfm
muon/_atac/_ref/jaspar/MA0063.2.pfm
muon/_atac/_ref/jaspar/MA0065.2.pfm
muon/_atac/_ref/jaspar/MA0066.1.pfm
muon/_atac/_ref/jaspar/MA0067.1.pfm
muon/_atac/_ref/jaspar/MA0068.2.pfm
muon/_atac/_ref/jaspar/MA0069.1.pfm
muon/_atac/_ref/jaspar/MA0070.1.pfm
muon/_atac/_ref/jaspar/MA0071.1.pfm
muon/_atac/_ref/jaspar/MA0072.1.pfm
muon/_atac/_ref/jaspar/MA0073.1.pfm
muon-0.1.7.dist-info/WHEEL
muon-0.1.7.dist-info/METADATA
muon-0.1.7.dist-info/RECORD
