Metadata-Version: 2.1
Name: muon
Version: 0.1.7
Summary: Multimodal omics analysis framework
Home-page: https://github.com/scverse/muon
Author: Danila Bredikhin
Author-email: danila.bredikhin@embl.de
Requires-Python: >= 3.10
Classifier: Programming Language :: Python :: 3
Classifier: License :: OSI Approved :: BSD License
Classifier: Operating System :: OS Independent
Classifier: Development Status :: 3 - Alpha
Classifier: Topic :: Scientific/Engineering :: Bio-Informatics
Classifier: Intended Audience :: Science/Research
Requires-Dist: numpy
Requires-Dist: pandas
Requires-Dist: matplotlib
Requires-Dist: seaborn
Requires-Dist: h5py
Requires-Dist: anndata
Requires-Dist: scanpy
Requires-Dist: scikit-learn
Requires-Dist: umap-learn
Requires-Dist: numba
Requires-Dist: protobuf
Requires-Dist: tqdm
Requires-Dist: mudata
Requires-Dist: pybedtools ; extra == "atac"
Requires-Dist: pysam ; extra == "atac"
Requires-Dist: sphinx >= 4.0 ; extra == "docs"
Requires-Dist: pydata-sphinx-theme==0.8.1 ; extra == "docs"
Requires-Dist: sphinx-book-theme==0.3.3 ; extra == "docs"
Requires-Dist: readthedocs-sphinx-search ; extra == "docs"
Requires-Dist: nbsphinx ; extra == "docs"
Requires-Dist: sphinx_automodapi ; extra == "docs"
Requires-Dist: pytest ; extra == "test"
Requires-Dist: flake8 ; extra == "test"
Requires-Dist: mofapy2 ; extra == "test"
Project-URL: Documentation, https://muon.readthedocs.io/en/latest/
Provides-Extra: atac
Provides-Extra: docs
Provides-Extra: test
